mtc_cli/__init__.py
mtc_cli/__main__.py
mtc_cli-0.2.0.dist-info/LICENSE.md
mtc_cli-0.2.0.dist-info/METADATA
mtc_cli-0.2.0.dist-info/WHEEL
mtc_cli-0.2.0.dist-info/entry_points.txt
mtc_cli-0.2.0.dist-info/top_level.txt
mtc_cli-0.2.0.dist-info/RECORD
