Metadata-Version: 2.1
Name: mtc-cli
Version: 0.2.0
Summary: A simple CLI tool for moving enwp files to Commons
Home-page: https://github.com/fastily/mtc-cli
Author: Fastily
Author-email: fastily@users.noreply.github.com
Project-URL: Bug Tracker, https://github.com/fastily/mtc-cli/issues
Classifier: Natural Language :: English
Classifier: Programming Language :: Python :: 3
Classifier: Programming Language :: Python :: 3.12
Classifier: License :: OSI Approved :: GNU General Public License v3 (GPLv3)
Classifier: Operating System :: OS Independent
Requires-Python: >=3.12
License-File: LICENSE.md
Requires-Dist: pwiki
Requires-Dist: rich
